{
  "data": [
    {
      "grand_total": {
        "hours": 5,
        "minutes": 53,
        "total_seconds": 21203.470442,
        "digital": "5:53",
        "decimal": "5.88",
        "text": "5 hrs 53 mins"
      },
      "range": {
        "start": "2025-02-28T23:00:00Z",
        "end": "2025-03-01T22:59:59Z",
        "date": "2025-03-01",
        "text": "Sat Mar 1st 2025",
        "timezone": "Europe/Oslo"
      },
      "projects": [
        {
          "name": "engine-software-2025-v0",
          "total_seconds": 15941.90913,
          "color": null,
          "digital": "4:25:41",
          "decimal": "4.42",
          "text": "4 hrs 25 mins",
          "hours": 4,
          "minutes": 25,
          "seconds": 41,
          "percent": 75.19
        },
        {
          "name": "engine-software-2025-thermocouple-driver-max31856",
          "total_seconds": 4635.93848,
          "color": null,
          "digital": "1:17:15",
          "decimal": "1.28",
          "text": "1 hr 17 mins",
          "hours": 1,
          "minutes": 17,
          "seconds": 15,
          "percent": 21.86
        },
        {
          "name": "gjallarhorn",
          "total_seconds": 481.207672,
          "color": null,
          "digital": "0:08:01",
          "decimal": "0.13",
          "text": "8 mins",
          "hours": 0,
          "minutes": 8,
          "seconds": 1,
          "percent": 2.27
        },
        {
          "name": "rtos-docs",
          "total_seconds": 102.475907,
          "color": null,
          "digital": "0:01:42",
          "decimal": "0.02",
          "text": "1 min",
          "hours": 0,
          "minutes": 1,
          "seconds": 42,
          "percent": 0.48
        },
        {
          "name": "latex-renderer",
          "total_seconds": 41.939253,
          "color": null,
          "digital": "0:00:41",
          "decimal": "0.00",
          "text": "41 secs",
          "hours": 0,
          "minutes": 0,
          "seconds": 41,
          "percent": 0.2
        }
      ],
      "languages": [
        {
          "name": "C",
          "total_seconds": 18564.827793,
          "digital": "5:09:24",
          "decimal": "5.15",
          "text": "5 hrs 9 mins",
          "hours": 5,
          "minutes": 9,
          "seconds": 24,
          "percent": 87.56
        },
        {
          "name": "Other",
          "total_seconds": 1712.542059,
          "digital": "0:28:32",
          "decimal": "0.47",
          "text": "28 mins",
          "hours": 0,
          "minutes": 28,
          "seconds": 32,
          "percent": 8.08
        },
        {
          "name": "S",
          "total_seconds": 544.92088,
          "digital": "0:09:04",
          "decimal": "0.15",
          "text": "9 mins",
          "hours": 0,
          "minutes": 9,
          "seconds": 4,
          "percent": 2.57
        },
        {
          "name": "Markdown",
          "total_seconds": 123.589919,
          "digital": "0:02:03",
          "decimal": "0.03",
          "text": "2 mins",
          "hours": 0,
          "minutes": 2,
          "seconds": 3,
          "percent": 0.58
        },
        {
          "name": "CMake",
          "total_seconds": 118.502622,
          "digital": "0:01:58",
          "decimal": "0.02",
          "text": "1 min",
          "hours": 0,
          "minutes": 1,
          "seconds": 58,
          "percent": 0.56
        },
        {
          "name": "Assembly",
          "total_seconds": 64.334957,
          "digital": "0:01:04",
          "decimal": "0.02",
          "text": "1 min",
          "hours": 0,
          "minutes": 1,
          "seconds": 4,
          "percent": 0.3
        },
        {
          "name": "Svelte",
          "total_seconds": 41.939253,
          "digital": "0:00:41",
          "decimal": "0.00",
          "text": "41 secs",
          "hours": 0,
          "minutes": 0,
          "seconds": 41,
          "percent": 0.2
        },
        {
          "name": "JSON",
          "total_seconds": 29.895059,
          "digital": "0:00:29",
          "decimal": "0.00",
          "text": "29 secs",
          "hours": 0,
          "minutes": 0,
          "seconds": 29,
          "percent": 0.14
        },
        {
          "name": "ca65 assembler",
          "total_seconds": 1.564281,
          "digital": "0:00:01",
          "decimal": "0.00",
          "text": "1 sec",
          "hours": 0,
          "minutes": 0,
          "seconds": 1,
          "percent": 0.01
        },
        {
          "name": "Objective-C",
          "total_seconds": 1.353619,
          "digital": "0:00:01",
          "decimal": "0.00",
          "text": "1 sec",
          "hours": 0,
          "minutes": 0,
          "seconds": 1,
          "percent": 0.01
        }
      ],
      "dependencies": [
        {
          "name": "thermo",
          "total_seconds": 11162.060401,
          "digital": "3:06:02",
          "decimal": "3.10",
          "text": "3 hrs 6 mins",
          "hours": 3,
          "minutes": 6,
          "seconds": 2,
          "percent": 14.71
        },
        {
          "name": "stdint",
          "total_seconds": 4288.438932,
          "digital": "1:11:28",
          "decimal": "1.18",
          "text": "1 hr 11 mins",
          "hours": 1,
          "minutes": 11,
          "seconds": 28,
          "percent": 5.65
        },
        {
          "name": "main",
          "total_seconds": 3962.964453,
          "digital": "1:06:02",
          "decimal": "1.10",
          "text": "1 hr 6 mins",
          "hours": 1,
          "minutes": 6,
          "seconds": 2,
          "percent": 5.22
        },
        {
          "name": "pressure",
          "total_seconds": 3429.308932,
          "digital": "0:57:09",
          "decimal": "0.95",
          "text": "57 mins",
          "hours": 0,
          "minutes": 57,
          "seconds": 9,
          "percent": 4.52
        },
        {
          "name": "threadpool",
          "total_seconds": 2992.677482,
          "digital": "0:49:52",
          "decimal": "0.82",
          "text": "49 mins",
          "hours": 0,
          "minutes": 49,
          "seconds": 52,
          "percent": 3.95
        },
        {
          "name": "fsm",
          "total_seconds": 2868.471604,
          "digital": "0:47:48",
          "decimal": "0.78",
          "text": "47 mins",
          "hours": 0,
          "minutes": 47,
          "seconds": 48,
          "percent": 3.78
        },
        {
          "name": "app_threadx",
          "total_seconds": 2826.462486,
          "digital": "0:47:06",
          "decimal": "0.78",
          "text": "47 mins",
          "hours": 0,
          "minutes": 47,
          "seconds": 6,
          "percent": 3.73
        },
        {
          "name": "encoder",
          "total_seconds": 1967.489467,
          "digital": "0:32:47",
          "decimal": "0.53",
          "text": "32 mins",
          "hours": 0,
          "minutes": 32,
          "seconds": 47,
          "percent": 2.59
        },
        {
          "name": "autovent",
          "total_seconds": 1879.643163,
          "digital": "0:31:19",
          "decimal": "0.52",
          "text": "31 mins",
          "hours": 0,
          "minutes": 31,
          "seconds": 19,
          "percent": 2.48
        },
        {
          "name": "status",
          "total_seconds": 1867.592314,
          "digital": "0:31:07",
          "decimal": "0.52",
          "text": "31 mins",
          "hours": 0,
          "minutes": 31,
          "seconds": 7,
          "percent": 2.46
        },
        {
          "name": "can-data",
          "total_seconds": 1865.871797,
          "digital": "0:31:05",
          "decimal": "0.52",
          "text": "31 mins",
          "hours": 0,
          "minutes": 31,
          "seconds": 5,
          "percent": 2.46
        },
        {
          "name": "reset",
          "total_seconds": 1864.944181,
          "digital": "0:31:04",
          "decimal": "0.52",
          "text": "31 mins",
          "hours": 0,
          "minutes": 31,
          "seconds": 4,
          "percent": 2.46
        },
        {
          "name": "cliudp",
          "total_seconds": 1864.944181,
          "digital": "0:31:04",
          "decimal": "0.52",
          "text": "31 mins",
          "hours": 0,
          "minutes": 31,
          "seconds": 4,
          "percent": 2.46
        },
        {
          "name": "ereg",
          "total_seconds": 1862.741295,
          "digital": "0:31:02",
          "decimal": "0.52",
          "text": "31 mins",
          "hours": 0,
          "minutes": 31,
          "seconds": 2,
          "percent": 2.46
        },
        {
          "name": "utilities",
          "total_seconds": 1561.902932,
          "digital": "0:26:01",
          "decimal": "0.43",
          "text": "26 mins",
          "hours": 0,
          "minutes": 26,
          "seconds": 1,
          "percent": 2.06
        },
        {
          "name": "MAX31856",
          "total_seconds": 1473.880269,
          "digital": "0:24:33",
          "decimal": "0.40",
          "text": "24 mins",
          "hours": 0,
          "minutes": 24,
          "seconds": 33,
          "percent": 1.94
        },
        {
          "name": "cli",
          "total_seconds": 1283.101285,
          "digital": "0:21:23",
          "decimal": "0.35",
          "text": "21 mins",
          "hours": 0,
          "minutes": 21,
          "seconds": 23,
          "percent": 1.69
        },
        {
          "name": "leveldriver",
          "total_seconds": 1218.405609,
          "digital": "0:20:18",
          "decimal": "0.33",
          "text": "20 mins",
          "hours": 0,
          "minutes": 20,
          "seconds": 18,
          "percent": 1.61
        },
        {
          "name": "pressurecmd",
          "total_seconds": 1097.612696,
          "digital": "0:18:17",
          "decimal": "0.30",
          "text": "18 mins",
          "hours": 0,
          "minutes": 18,
          "seconds": 17,
          "percent": 1.45
        },
        {
          "name": "bldccmd",
          "total_seconds": 1089.344142,
          "digital": "0:18:09",
          "decimal": "0.30",
          "text": "18 mins",
          "hours": 0,
          "minutes": 18,
          "seconds": 9,
          "percent": 1.44
        },
        {
          "name": "fsmcmd",
          "total_seconds": 1082.486883,
          "digital": "0:18:02",
          "decimal": "0.30",
          "text": "18 mins",
          "hours": 0,
          "minutes": 18,
          "seconds": 2,
          "percent": 1.43
        },
        {
          "name": "consolecmd",
          "total_seconds": 1072.880119,
          "digital": "0:17:52",
          "decimal": "0.28",
          "text": "17 mins",
          "hours": 0,
          "minutes": 17,
          "seconds": 52,
          "percent": 1.41
        },
        {
          "name": "solenoidcmd",
          "total_seconds": 1069.753767,
          "digital": "0:17:49",
          "decimal": "0.28",
          "text": "17 mins",
          "hours": 0,
          "minutes": 17,
          "seconds": 49,
          "percent": 1.41
        },
        {
          "name": "servocmd",
          "total_seconds": 1069.753767,
          "digital": "0:17:49",
          "decimal": "0.28",
          "text": "17 mins",
          "hours": 0,
          "minutes": 17,
          "seconds": 49,
          "percent": 1.41
        },
        {
          "name": "syscmd",
          "total_seconds": 1069.753767,
          "digital": "0:17:49",
          "decimal": "0.28",
          "text": "17 mins",
          "hours": 0,
          "minutes": 17,
          "seconds": 49,
          "percent": 1.41
        },
        {
          "name": "loadcelldriver",
          "total_seconds": 1069.753767,
          "digital": "0:17:49",
          "decimal": "0.28",
          "text": "17 mins",
          "hours": 0,
          "minutes": 17,
          "seconds": 49,
          "percent": 1.41
        },
        {
          "name": "eregcmd",
          "total_seconds": 1069.753767,
          "digital": "0:17:49",
          "decimal": "0.28",
          "text": "17 mins",
          "hours": 0,
          "minutes": 17,
          "seconds": 49,
          "percent": 1.41
        },
        {
          "name": "easingfunctions",
          "total_seconds": 976.095325,
          "digital": "0:16:16",
          "decimal": "0.27",
          "text": "16 mins",
          "hours": 0,
          "minutes": 16,
          "seconds": 16,
          "percent": 1.29
        },
        {
          "name": "tx_api",
          "total_seconds": 774.735216,
          "digital": "0:12:54",
          "decimal": "0.20",
          "text": "12 mins",
          "hours": 0,
          "minutes": 12,
          "seconds": 54,
          "percent": 1.02
        },
        {
          "name": "fdcandriver",
          "total_seconds": 773.8661,
          "digital": "0:12:53",
          "decimal": "0.20",
          "text": "12 mins",
          "hours": 0,
          "minutes": 12,
          "seconds": 53,
          "percent": 1.02
        },
        {
          "name": "spi",
          "total_seconds": 654.780316,
          "digital": "0:10:54",
          "decimal": "0.17",
          "text": "10 mins",
          "hours": 0,
          "minutes": 10,
          "seconds": 54,
          "percent": 0.86
        },
        {
          "name": "app_netxduo",
          "total_seconds": 646.787002,
          "digital": "0:10:46",
          "decimal": "0.17",
          "text": "10 mins",
          "hours": 0,
          "minutes": 10,
          "seconds": 46,
          "percent": 0.85
        },
        {
          "name": "fdcan",
          "total_seconds": 622.761557,
          "digital": "0:10:22",
          "decimal": "0.17",
          "text": "10 mins",
          "hours": 0,
          "minutes": 10,
          "seconds": 22,
          "percent": 0.82
        },
        {
          "name": "gpio",
          "total_seconds": 509.715202,
          "digital": "0:08:29",
          "decimal": "0.13",
          "text": "8 mins",
          "hours": 0,
          "minutes": 8,
          "seconds": 29,
          "percent": 0.67
        },
        {
          "name": "eth",
          "total_seconds": 489.548327,
          "digital": "0:08:09",
          "decimal": "0.13",
          "text": "8 mins",
          "hours": 0,
          "minutes": 8,
          "seconds": 9,
          "percent": 0.65
        },
        {
          "name": "quadspi",
          "total_seconds": 482.513519,
          "digital": "0:08:02",
          "decimal": "0.13",
          "text": "8 mins",
          "hours": 0,
          "minutes": 8,
          "seconds": 2,
          "percent": 0.64
        },
        {
          "name": "adc",
          "total_seconds": 482.513519,
          "digital": "0:08:02",
          "decimal": "0.13",
          "text": "8 mins",
          "hours": 0,
          "minutes": 8,
          "seconds": 2,
          "percent": 0.64
        },
        {
          "name": "memorymap",
          "total_seconds": 482.513519,
          "digital": "0:08:02",
          "decimal": "0.13",
          "text": "8 mins",
          "hours": 0,
          "minutes": 8,
          "seconds": 2,
          "percent": 0.64
        },
        {
          "name": "tim",
          "total_seconds": 482.513519,
          "digital": "0:08:02",
          "decimal": "0.13",
          "text": "8 mins",
          "hours": 0,
          "minutes": 8,
          "seconds": 2,
          "percent": 0.64
        },
        {
          "name": "dma",
          "total_seconds": 482.513519,
          "digital": "0:08:02",
          "decimal": "0.13",
          "text": "8 mins",
          "hours": 0,
          "minutes": 8,
          "seconds": 2,
          "percent": 0.64
        },
        {
          "name": "sdmmc",
          "total_seconds": 482.513519,
          "digital": "0:08:02",
          "decimal": "0.13",
          "text": "8 mins",
          "hours": 0,
          "minutes": 8,
          "seconds": 2,
          "percent": 0.64
        },
        {
          "name": "kalman",
          "total_seconds": 481.207672,
          "digital": "0:08:01",
          "decimal": "0.13",
          "text": "8 mins",
          "hours": 0,
          "minutes": 8,
          "seconds": 1,
          "percent": 0.63
        },
        {
          "name": "xbee",
          "total_seconds": 481.207672,
          "digital": "0:08:01",
          "decimal": "0.13",
          "text": "8 mins",
          "hours": 0,
          "minutes": 8,
          "seconds": 1,
          "percent": 0.63
        },
        {
          "name": "navigation",
          "total_seconds": 481.207672,
          "digital": "0:08:01",
          "decimal": "0.13",
          "text": "8 mins",
          "hours": 0,
          "minutes": 8,
          "seconds": 1,
          "percent": 0.63
        },
        {
          "name": "FSM",
          "total_seconds": 481.207672,
          "digital": "0:08:01",
          "decimal": "0.13",
          "text": "8 mins",
          "hours": 0,
          "minutes": 8,
          "seconds": 1,
          "percent": 0.63
        },
        {
          "name": "storage",
          "total_seconds": 481.207672,
          "digital": "0:08:01",
          "decimal": "0.13",
          "text": "8 mins",
          "hours": 0,
          "minutes": 8,
          "seconds": 1,
          "percent": 0.63
        },
        {
          "name": "sensors",
          "total_seconds": 481.207672,
          "digital": "0:08:01",
          "decimal": "0.13",
          "text": "8 mins",
          "hours": 0,
          "minutes": 8,
          "seconds": 1,
          "percent": 0.63
        },
        {
          "name": "fdcanbus",
          "total_seconds": 481.207672,
          "digital": "0:08:01",
          "decimal": "0.13",
          "text": "8 mins",
          "hours": 0,
          "minutes": 8,
          "seconds": 1,
          "percent": 0.63
        },
        {
          "name": "stdbool",
          "total_seconds": 424.023214,
          "digital": "0:07:04",
          "decimal": "0.12",
          "text": "7 mins",
          "hours": 0,
          "minutes": 7,
          "seconds": 4,
          "percent": 0.56
        },
        {
          "name": "usart",
          "total_seconds": 394.232144,
          "digital": "0:06:34",
          "decimal": "0.10",
          "text": "6 mins",
          "hours": 0,
          "minutes": 6,
          "seconds": 34,
          "percent": 0.52
        },
        {
          "name": "i2c",
          "total_seconds": 394.232144,
          "digital": "0:06:34",
          "decimal": "0.10",
          "text": "6 mins",
          "hours": 0,
          "minutes": 6,
          "seconds": 34,
          "percent": 0.52
        },
        {
          "name": "stm32h7xx_it",
          "total_seconds": 348.962966,
          "digital": "0:05:48",
          "decimal": "0.08",
          "text": "5 mins",
          "hours": 0,
          "minutes": 5,
          "seconds": 48,
          "percent": 0.46
        },
        {
          "name": "stm32g4xx_hal",
          "total_seconds": 220.017561,
          "digital": "0:03:40",
          "decimal": "0.05",
          "text": "3 mins",
          "hours": 0,
          "minutes": 3,
          "seconds": 40,
          "percent": 0.29
        },
        {
          "name": "stm32h7xx_hal",
          "total_seconds": 203.909265,
          "digital": "0:03:23",
          "decimal": "0.05",
          "text": "3 mins",
          "hours": 0,
          "minutes": 3,
          "seconds": 23,
          "percent": 0.27
        },
        {
          "name": "errno",
          "total_seconds": 177.099133,
          "digital": "0:02:57",
          "decimal": "0.03",
          "text": "2 mins",
          "hours": 0,
          "minutes": 2,
          "seconds": 57,
          "percent": 0.23
        },
        {
          "name": "signal",
          "total_seconds": 177.099133,
          "digital": "0:02:57",
          "decimal": "0.03",
          "text": "2 mins",
          "hours": 0,
          "minutes": 2,
          "seconds": 57,
          "percent": 0.23
        },
        {
          "name": "sys",
          "total_seconds": 177.099133,
          "digital": "0:02:57",
          "decimal": "0.03",
          "text": "2 mins",
          "hours": 0,
          "minutes": 2,
          "seconds": 57,
          "percent": 0.23
        },
        {
          "name": "bldcdriver",
          "total_seconds": 173.220622,
          "digital": "0:02:53",
          "decimal": "0.03",
          "text": "2 mins",
          "hours": 0,
          "minutes": 2,
          "seconds": 53,
          "percent": 0.23
        },
        {
          "name": "stm32h7xx",
          "total_seconds": 138.680355,
          "digital": "0:02:18",
          "decimal": "0.03",
          "text": "2 mins",
          "hours": 0,
          "minutes": 2,
          "seconds": 18,
          "percent": 0.18
        },
        {
          "name": "app_azure_rtos",
          "total_seconds": 128.139539,
          "digital": "0:02:08",
          "decimal": "0.03",
          "text": "2 mins",
          "hours": 0,
          "minutes": 2,
          "seconds": 8,
          "percent": 0.17
        },
        {
          "name": "nx_stm32_phy_driver",
          "total_seconds": 119.99125,
          "digital": "0:01:59",
          "decimal": "0.02",
          "text": "1 min",
          "hours": 0,
          "minutes": 1,
          "seconds": 59,
          "percent": 0.16
        },
        {
          "name": "nx_stm32_eth_config",
          "total_seconds": 119.589637,
          "digital": "0:01:59",
          "decimal": "0.02",
          "text": "1 min",
          "hours": 0,
          "minutes": 1,
          "seconds": 59,
          "percent": 0.16
        },
        {
          "name": "tx_thread",
          "total_seconds": 108.640099,
          "digital": "0:01:48",
          "decimal": "0.02",
          "text": "1 min",
          "hours": 0,
          "minutes": 1,
          "seconds": 48,
          "percent": 0.14
        },
        {
          "name": "usb_otg",
          "total_seconds": 88.281375,
          "digital": "0:01:28",
          "decimal": "0.02",
          "text": "1 min",
          "hours": 0,
          "minutes": 1,
          "seconds": 28,
          "percent": 0.12
        },
        {
          "name": "lan8742",
          "total_seconds": 80.043855,
          "digital": "0:01:20",
          "decimal": "0.02",
          "text": "1 min",
          "hours": 0,
          "minutes": 1,
          "seconds": 20,
          "percent": 0.11
        },
        {
          "name": "config",
          "total_seconds": 74.476512,
          "digital": "0:01:14",
          "decimal": "0.02",
          "text": "1 min",
          "hours": 0,
          "minutes": 1,
          "seconds": 14,
          "percent": 0.1
        },
        {
          "name": "cliargs",
          "total_seconds": 63.308772,
          "digital": "0:01:03",
          "decimal": "0.02",
          "text": "1 min",
          "hours": 0,
          "minutes": 1,
          "seconds": 3,
          "percent": 0.08
        },
        {
          "name": "nxd_telnet_server",
          "total_seconds": 62.772946,
          "digital": "0:01:02",
          "decimal": "0.02",
          "text": "1 min",
          "hours": 0,
          "minutes": 1,
          "seconds": 2,
          "percent": 0.08
        },
        {
          "name": "assert",
          "total_seconds": 50.165714,
          "digital": "0:00:50",
          "decimal": "0.00",
          "text": "50 secs",
          "hours": 0,
          "minutes": 0,
          "seconds": 50,
          "percent": 0.07
        },
        {
          "name": "stdarg",
          "total_seconds": 37.424126,
          "digital": "0:00:37",
          "decimal": "0.00",
          "text": "37 secs",
          "hours": 0,
          "minutes": 0,
          "seconds": 37,
          "percent": 0.05
        },
        {
          "name": "tx_timer",
          "total_seconds": 34.784999,
          "digital": "0:00:34",
          "decimal": "0.00",
          "text": "34 secs",
          "hours": 0,
          "minutes": 0,
          "seconds": 34,
          "percent": 0.05
        },
        {
          "name": "tx_trace",
          "total_seconds": 33.315413,
          "digital": "0:00:33",
          "decimal": "0.00",
          "text": "33 secs",
          "hours": 0,
          "minutes": 0,
          "seconds": 33,
          "percent": 0.04
        },
        {
          "name": "ADS8674",
          "total_seconds": 31.006464,
          "digital": "0:00:31",
          "decimal": "0.00",
          "text": "31 secs",
          "hours": 0,
          "minutes": 0,
          "seconds": 31,
          "percent": 0.04
        },
        {
          "name": "stm32g4xx",
          "total_seconds": 26.775056,
          "digital": "0:00:26",
          "decimal": "0.00",
          "text": "26 secs",
          "hours": 0,
          "minutes": 0,
          "seconds": 26,
          "percent": 0.04
        },
        {
          "name": "servodriver",
          "total_seconds": 26.285586,
          "digital": "0:00:26",
          "decimal": "0.00",
          "text": "26 secs",
          "hours": 0,
          "minutes": 0,
          "seconds": 26,
          "percent": 0.03
        },
        {
          "name": "solenoiddriver",
          "total_seconds": 26.285586,
          "digital": "0:00:26",
          "decimal": "0.00",
          "text": "26 secs",
          "hours": 0,
          "minutes": 0,
          "seconds": 26,
          "percent": 0.03
        },
        {
          "name": "tx_ghs",
          "total_seconds": 20.046201,
          "digital": "0:00:20",
          "decimal": "0.00",
          "text": "20 secs",
          "hours": 0,
          "minutes": 0,
          "seconds": 20,
          "percent": 0.03
        },
        {
          "name": "arm_ghs",
          "total_seconds": 20.046201,
          "digital": "0:00:20",
          "decimal": "0.00",
          "text": "20 secs",
          "hours": 0,
          "minutes": 0,
          "seconds": 20,
          "percent": 0.03
        },
        {
          "name": "tx_user",
          "total_seconds": 20.046201,
          "digital": "0:00:20",
          "decimal": "0.00",
          "text": "20 secs",
          "hours": 0,
          "minutes": 0,
          "seconds": 20,
          "percent": 0.03
        },
        {
          "name": "intrinsics.h>",
          "total_seconds": 20.046201,
          "digital": "0:00:20",
          "decimal": "0.00",
          "text": "20 secs",
          "hours": 0,
          "minutes": 0,
          "seconds": 20,
          "percent": 0.03
        },
        {
          "name": "yvals",
          "total_seconds": 20.046201,
          "digital": "0:00:20",
          "decimal": "0.00",
          "text": "20 secs",
          "hours": 0,
          "minutes": 0,
          "seconds": 20,
          "percent": 0.03
        },
        {
          "name": "stm32h7xx_hal_def",
          "total_seconds": 19.574473,
          "digital": "0:00:19",
          "decimal": "0.00",
          "text": "19 secs",
          "hours": 0,
          "minutes": 0,
          "seconds": 19,
          "percent": 0.03
        },
        {
          "name": "assert.h>",
          "total_seconds": 13.978713,
          "digital": "0:00:13",
          "decimal": "0.00",
          "text": "13 secs",
          "hours": 0,
          "minutes": 0,
          "seconds": 13,
          "percent": 0.02
        },
        {
          "name": "nx_stm32_eth_driver",
          "total_seconds": 12.105179,
          "digital": "0:00:12",
          "decimal": "0.00",
          "text": "12 secs",
          "hours": 0,
          "minutes": 0,
          "seconds": 12,
          "percent": 0.02
        },
        {
          "name": "clitelnet",
          "total_seconds": 11.703566,
          "digital": "0:00:11",
          "decimal": "0.00",
          "text": "11 secs",
          "hours": 0,
          "minutes": 0,
          "seconds": 11,
          "percent": 0.02
        },
        {
          "name": "stdio.h>",
          "total_seconds": 10.574734,
          "digital": "0:00:10",
          "decimal": "0.00",
          "text": "10 secs",
          "hours": 0,
          "minutes": 0,
          "seconds": 10,
          "percent": 0.01
        },
        {
          "name": "Legacy",
          "total_seconds": 10.540816,
          "digital": "0:00:10",
          "decimal": "0.00",
          "text": "10 secs",
          "hours": 0,
          "minutes": 0,
          "seconds": 10,
          "percent": 0.01
        },
        {
          "name": "stddef",
          "total_seconds": 10.540816,
          "digital": "0:00:10",
          "decimal": "0.00",
          "text": "10 secs",
          "hours": 0,
          "minutes": 0,
          "seconds": 10,
          "percent": 0.01
        },
        {
          "name": "math",
          "total_seconds": 10.540816,
          "digital": "0:00:10",
          "decimal": "0.00",
          "text": "10 secs",
          "hours": 0,
          "minutes": 0,
          "seconds": 10,
          "percent": 0.01
        },
        {
          "name": "stdbool.h>",
          "total_seconds": 9.383718,
          "digital": "0:00:09",
          "decimal": "0.00",
          "text": "9 secs",
          "hours": 0,
          "minutes": 0,
          "seconds": 9,
          "percent": 0.01
        },
        {
          "name": "main.h\"",
          "total_seconds": 9.383718,
          "digital": "0:00:09",
          "decimal": "0.00",
          "text": "9 secs",
          "hours": 0,
          "minutes": 0,
          "seconds": 9,
          "percent": 0.01
        },
        {
          "name": "stm32h753xx",
          "total_seconds": 7.034808,
          "digital": "0:00:07",
          "decimal": "0.00",
          "text": "7 secs",
          "hours": 0,
          "minutes": 0,
          "seconds": 7,
          "percent": 0.01
        },
        {
          "name": "nx_api",
          "total_seconds": 6.870628,
          "digital": "0:00:06",
          "decimal": "0.00",
          "text": "6 secs",
          "hours": 0,
          "minutes": 0,
          "seconds": 6,
          "percent": 0.01
        },
        {
          "name": "all_tests",
          "total_seconds": 6.129841,
          "digital": "0:00:06",
          "decimal": "0.00",
          "text": "6 secs",
          "hours": 0,
          "minutes": 0,
          "seconds": 6,
          "percent": 0.01
        },
        {
          "name": "jtest",
          "total_seconds": 6.129841,
          "digital": "0:00:06",
          "decimal": "0.00",
          "text": "6 secs",
          "hours": 0,
          "minutes": 0,
          "seconds": 6,
          "percent": 0.01
        },
        {
          "name": "arm_math",
          "total_seconds": 6.129841,
          "digital": "0:00:06",
          "decimal": "0.00",
          "text": "6 secs",
          "hours": 0,
          "minutes": 0,
          "seconds": 6,
          "percent": 0.01
        },
        {
          "name": "_ansi",
          "total_seconds": 3.313347,
          "digital": "0:00:03",
          "decimal": "0.00",
          "text": "3 secs",
          "hours": 0,
          "minutes": 0,
          "seconds": 3,
          "percent": 0
        },
        {
          "name": "stm32h7xx_hal_gpio_ex",
          "total_seconds": 2.735071,
          "digital": "0:00:02",
          "decimal": "0.00",
          "text": "2 secs",
          "hours": 0,
          "minutes": 0,
          "seconds": 2,
          "percent": 0
        },
        {
          "name": "nx_ip",
          "total_seconds": 2.019609,
          "digital": "0:00:02",
          "decimal": "0.00",
          "text": "2 secs",
          "hours": 0,
          "minutes": 0,
          "seconds": 2,
          "percent": 0
        },
        {
          "name": "nx_udp",
          "total_seconds": 2.019609,
          "digital": "0:00:02",
          "decimal": "0.00",
          "text": "2 secs",
          "hours": 0,
          "minutes": 0,
          "seconds": 2,
          "percent": 0
        },
        {
          "name": "rt_misc",
          "total_seconds": 1.664956,
          "digital": "0:00:01",
          "decimal": "0.00",
          "text": "1 sec",
          "hours": 0,
          "minutes": 0,
          "seconds": 1,
          "percent": 0
        },
        {
          "name": "Serial",
          "total_seconds": 1.664956,
          "digital": "0:00:01",
          "decimal": "0.00",
          "text": "1 sec",
          "hours": 0,
          "minutes": 0,
          "seconds": 1,
          "percent": 0
        },
        {
          "name": "stm32h7xx_hal_adc_ex",
          "total_seconds": 1.519856,
          "digital": "0:00:01",
          "decimal": "0.00",
          "text": "1 sec",
          "hours": 0,
          "minutes": 0,
          "seconds": 1,
          "percent": 0
        },
        {
          "name": "stm32h7xx_ll_adc",
          "total_seconds": 1.519856,
          "digital": "0:00:01",
          "decimal": "0.00",
          "text": "1 sec",
          "hours": 0,
          "minutes": 0,
          "seconds": 1,
          "percent": 0
        },
        {
          "name": "tx_initialize",
          "total_seconds": 1.469586,
          "digital": "0:00:01",
          "decimal": "0.00",
          "text": "1 sec",
          "hours": 0,
          "minutes": 0,
          "seconds": 1,
          "percent": 0
        },
        {
          "name": "jtest_group",
          "total_seconds": 1.191016,
          "digital": "0:00:01",
          "decimal": "0.00",
          "text": "1 sec",
          "hours": 0,
          "minutes": 0,
          "seconds": 1,
          "percent": 0
        },
        {
          "name": "jtest_pf.h\"",
          "total_seconds": 1.191016,
          "digital": "0:00:01",
          "decimal": "0.00",
          "text": "1 sec",
          "hours": 0,
          "minutes": 0,
          "seconds": 1,
          "percent": 0
        },
        {
          "name": "stdint.h>",
          "total_seconds": 1.191016,
          "digital": "0:00:01",
          "decimal": "0.00",
          "text": "1 sec",
          "hours": 0,
          "minutes": 0,
          "seconds": 1,
          "percent": 0
        },
        {
          "name": "string.h>",
          "total_seconds": 1.191016,
          "digital": "0:00:01",
          "decimal": "0.00",
          "text": "1 sec",
          "hours": 0,
          "minutes": 0,
          "seconds": 1,
          "percent": 0
        }
      ],
      "machines": [
        {
          "name": "ngb",
          "total_seconds": 21203.470442,
          "machine_name_id": "187acaf3-e3c6-4b6d-ab77-4d9cd4a079e2",
          "digital": "5:53:23",
          "decimal": "5.88",
          "text": "5 hrs 53 mins",
          "hours": 5,
          "minutes": 53,
          "seconds": 23,
          "percent": 100
        }
      ],
      "editors": [
        {
          "name": "VS Code",
          "total_seconds": 21203.470442,
          "digital": "5:53:23",
          "decimal": "5.88",
          "text": "5 hrs 53 mins",
          "hours": 5,
          "minutes": 53,
          "seconds": 23,
          "percent": 100
        }
      ],
      "operating_systems": [
        {
          "name": "Windows",
          "total_seconds": 21203.470442,
          "digital": "5:53:23",
          "decimal": "5.88",
          "text": "5 hrs 53 mins",
          "hours": 5,
          "minutes": 53,
          "seconds": 23,
          "percent": 100
        }
      ],
      "categories": [
        {
          "name": "Coding",
          "total_seconds": 13626.574948,
          "digital": "3:47:06",
          "decimal": "3.78",
          "text": "3 hrs 47 mins",
          "hours": 3,
          "minutes": 47,
          "seconds": 6,
          "percent": 64.27
        },
        {
          "name": "Debugging",
          "total_seconds": 7292.603564,
          "digital": "2:01:32",
          "decimal": "2.02",
          "text": "2 hrs 1 min",
          "hours": 2,
          "minutes": 1,
          "seconds": 32,
          "percent": 34.39
        },
        {
          "name": "Building",
          "total_seconds": 284.29193,
          "digital": "0:04:44",
          "decimal": "0.07",
          "text": "4 mins",
          "hours": 0,
          "minutes": 4,
          "seconds": 44,
          "percent": 1.34
        }
      ]
    }
  ],
  "start": "2025-02-28T23:00:00Z",
  "end": "2025-03-01T22:59:59Z",
  "cumulative_total": {
    "seconds": 21203.470442,
    "text": "5 hrs 53 mins",
    "digital": "5:53",
    "decimal": "5.88"
  },
  "daily_average": {
    "holidays": 0,
    "days_minus_holidays": 1,
    "days_including_holidays": 1,
    "seconds": 19491,
    "seconds_including_other_language": 21203,
    "text": "5 hrs 24 mins",
    "text_including_other_language": "5 hrs 53 mins"
  }
}