{
  "data": [
    {
      "grand_total": {
        "hours": 1,
        "minutes": 58,
        "total_seconds": 7138.853156,
        "digital": "1:58",
        "decimal": "1.97",
        "text": "1 hr 58 mins"
      },
      "range": {
        "start": "2025-03-26T23:00:00Z",
        "end": "2025-03-27T22:59:59Z",
        "date": "2025-03-27",
        "text": "Thu Mar 27th 2025",
        "timezone": "Europe/Oslo"
      },
      "projects": [
        {
          "name": "Uni",
          "total_seconds": 5178,
          "color": null,
          "digital": "1:26:18",
          "decimal": "1.43",
          "text": "1 hr 26 mins",
          "hours": 1,
          "minutes": 26,
          "seconds": 18,
          "percent": 72.53
        },
        {
          "name": "option-pricing-MCS",
          "total_seconds": 1731.785723,
          "color": null,
          "digital": "0:28:51",
          "decimal": "0.47",
          "text": "28 mins",
          "hours": 0,
          "minutes": 28,
          "seconds": 51,
          "percent": 24.26
        },
        {
          "name": "Unknown Project",
          "total_seconds": 117,
          "color": null,
          "digital": "0:01:57",
          "decimal": "0.02",
          "text": "1 min",
          "hours": 0,
          "minutes": 1,
          "seconds": 57,
          "percent": 1.64
        },
        {
          "name": "trading-bot",
          "total_seconds": 112.067433,
          "color": null,
          "digital": "0:01:52",
          "decimal": "0.02",
          "text": "1 min",
          "hours": 0,
          "minutes": 1,
          "seconds": 52,
          "percent": 1.57
        }
      ],
      "languages": [
        {
          "name": "Python",
          "total_seconds": 6531.811196,
          "digital": "1:48:51",
          "decimal": "1.80",
          "text": "1 hr 48 mins",
          "hours": 1,
          "minutes": 48,
          "seconds": 51,
          "percent": 91.5
        },
        {
          "name": "Markdown",
          "total_seconds": 469.004506,
          "digital": "0:07:49",
          "decimal": "0.12",
          "text": "7 mins",
          "hours": 0,
          "minutes": 7,
          "seconds": 49,
          "percent": 6.57
        },
        {
          "name": "INI",
          "total_seconds": 72,
          "digital": "0:01:12",
          "decimal": "0.02",
          "text": "1 min",
          "hours": 0,
          "minutes": 1,
          "seconds": 12,
          "percent": 1.01
        },
        {
          "name": "Lua",
          "total_seconds": 45,
          "digital": "0:00:45",
          "decimal": "0.00",
          "text": "45 secs",
          "hours": 0,
          "minutes": 0,
          "seconds": 45,
          "percent": 0.63
        },
        {
          "name": "Other",
          "total_seconds": 21.037454,
          "digital": "0:00:21",
          "decimal": "0.00",
          "text": "21 secs",
          "hours": 0,
          "minutes": 0,
          "seconds": 21,
          "percent": 0.29
        }
      ],
      "dependencies": [
        {
          "name": "numpy",
          "total_seconds": 4777.464418,
          "digital": "1:19:37",
          "decimal": "1.32",
          "text": "1 hr 19 mins",
          "hours": 1,
          "minutes": 19,
          "seconds": 37,
          "percent": 54.63
        },
        {
          "name": "matplotlib",
          "total_seconds": 1033.045172,
          "digital": "0:17:13",
          "decimal": "0.28",
          "text": "17 mins",
          "hours": 0,
          "minutes": 17,
          "seconds": 13,
          "percent": 11.81
        },
        {
          "name": "subprocess",
          "total_seconds": 656,
          "digital": "0:10:56",
          "decimal": "0.17",
          "text": "10 mins",
          "hours": 0,
          "minutes": 10,
          "seconds": 56,
          "percent": 7.5
        },
        {
          "name": "pandas",
          "total_seconds": 415.067433,
          "digital": "0:06:55",
          "decimal": "0.10",
          "text": "6 mins",
          "hours": 0,
          "minutes": 6,
          "seconds": 55,
          "percent": 4.75
        },
        {
          "name": "scipy",
          "total_seconds": 403.942785,
          "digital": "0:06:43",
          "decimal": "0.10",
          "text": "6 mins",
          "hours": 0,
          "minutes": 6,
          "seconds": 43,
          "percent": 4.62
        },
        {
          "name": "ink",
          "total_seconds": 297,
          "digital": "0:04:57",
          "decimal": "0.07",
          "text": "4 mins",
          "hours": 0,
          "minutes": 4,
          "seconds": 57,
          "percent": 3.4
        },
        {
          "name": "dek",
          "total_seconds": 297,
          "digital": "0:04:57",
          "decimal": "0.07",
          "text": "4 mins",
          "hours": 0,
          "minutes": 4,
          "seconds": 57,
          "percent": 3.4
        },
        {
          "name": "plot",
          "total_seconds": 221,
          "digital": "0:03:41",
          "decimal": "0.05",
          "text": "3 mins",
          "hours": 0,
          "minutes": 3,
          "seconds": 41,
          "percent": 2.53
        },
        {
          "name": "datetime",
          "total_seconds": 112.067433,
          "digital": "0:01:52",
          "decimal": "0.02",
          "text": "1 min",
          "hours": 0,
          "minutes": 1,
          "seconds": 52,
          "percent": 1.28
        },
        {
          "name": "dotenv",
          "total_seconds": 112.067433,
          "digital": "0:01:52",
          "decimal": "0.02",
          "text": "1 min",
          "hours": 0,
          "minutes": 1,
          "seconds": 52,
          "percent": 1.28
        },
        {
          "name": "time",
          "total_seconds": 112.067433,
          "digital": "0:01:52",
          "decimal": "0.02",
          "text": "1 min",
          "hours": 0,
          "minutes": 1,
          "seconds": 52,
          "percent": 1.28
        },
        {
          "name": "alpaca_trade_api",
          "total_seconds": 112.067433,
          "digital": "0:01:52",
          "decimal": "0.02",
          "text": "1 min",
          "hours": 0,
          "minutes": 1,
          "seconds": 52,
          "percent": 1.28
        },
        {
          "name": "black_scholes",
          "total_seconds": 103.012566,
          "digital": "0:01:43",
          "decimal": "0.02",
          "text": "1 min",
          "hours": 0,
          "minutes": 1,
          "seconds": 43,
          "percent": 1.18
        },
        {
          "name": "typing",
          "total_seconds": 73.309276,
          "digital": "0:01:13",
          "decimal": "0.02",
          "text": "1 min",
          "hours": 0,
          "minutes": 1,
          "seconds": 13,
          "percent": 0.84
        },
        {
          "name": "fromBS_call",
          "total_seconds": 6.10394,
          "digital": "0:00:06",
          "decimal": "0.00",
          "text": "6 secs",
          "hours": 0,
          "minutes": 0,
          "seconds": 6,
          "percent": 0.07
        },
        {
          "name": "BS_put",
          "total_seconds": 6.10394,
          "digital": "0:00:06",
          "decimal": "0.00",
          "text": "6 secs",
          "hours": 0,
          "minutes": 0,
          "seconds": 6,
          "percent": 0.07
        },
        {
          "name": "s",
          "total_seconds": 5.195626,
          "digital": "0:00:05",
          "decimal": "0.00",
          "text": "5 secs",
          "hours": 0,
          "minutes": 0,
          "seconds": 5,
          "percent": 0.06
        },
        {
          "name": "norm",
          "total_seconds": 2.213402,
          "digital": "0:00:02",
          "decimal": "0.00",
          "text": "2 secs",
          "hours": 0,
          "minutes": 0,
          "seconds": 2,
          "percent": 0.03
        }
      ],
      "machines": [
        {
          "name": "Nikolais-Mac-mini.local",
          "total_seconds": 7138.853156,
          "machine_name_id": "8e4f98f0-d325-4088-af2f-e0ee5b89dfda",
          "digital": "1:58:58",
          "decimal": "1.97",
          "text": "1 hr 58 mins",
          "hours": 1,
          "minutes": 58,
          "seconds": 58,
          "percent": 100
        }
      ],
      "editors": [
        {
          "name": "Neovim",
          "total_seconds": 5380.067433,
          "digital": "1:29:40",
          "decimal": "1.48",
          "text": "1 hr 29 mins",
          "hours": 1,
          "minutes": 29,
          "seconds": 40,
          "percent": 75.36
        },
        {
          "name": "VS Code",
          "total_seconds": 1731.785723,
          "digital": "0:28:51",
          "decimal": "0.47",
          "text": "28 mins",
          "hours": 0,
          "minutes": 28,
          "seconds": 51,
          "percent": 24.26
        },
        {
          "name": "Unknown Editor",
          "total_seconds": 27,
          "digital": "0:00:27",
          "decimal": "0.00",
          "text": "27 secs",
          "hours": 0,
          "minutes": 0,
          "seconds": 27,
          "percent": 0.38
        }
      ],
      "operating_systems": [
        {
          "name": "Mac",
          "total_seconds": 7138.853156,
          "digital": "1:58:58",
          "decimal": "1.97",
          "text": "1 hr 58 mins",
          "hours": 1,
          "minutes": 58,
          "seconds": 58,
          "percent": 100
        }
      ],
      "categories": [
        {
          "name": "Coding",
          "total_seconds": 7138.853156,
          "digital": "1:58:58",
          "decimal": "1.97",
          "text": "1 hr 58 mins",
          "hours": 1,
          "minutes": 58,
          "seconds": 58,
          "percent": 100
        }
      ]
    }
  ],
  "start": "2025-03-26T23:00:00Z",
  "end": "2025-03-27T22:59:59Z",
  "cumulative_total": {
    "seconds": 7138.853156,
    "text": "1 hr 58 mins",
    "digital": "1:58",
    "decimal": "1.97"
  },
  "daily_average": {
    "holidays": 0,
    "days_minus_holidays": 1,
    "days_including_holidays": 1,
    "seconds": 7118,
    "seconds_including_other_language": 7139,
    "text": "1 hr 58 mins",
    "text_including_other_language": "1 hr 58 mins"
  }
}