[
  {
    "id": "90f13ce8-921c-4308-af50-f31a6aac0237",
    "entity": "/Users/nikolaiborbe/Documents/Complexity/mimir/src/main.py",
    "type": "file",
    "time": 1744225512.474592,
    "project": "mimir",
    "project_root_count": 6,
    "branch": "main",
    "language": "Python",
    "dependencies": [
      "numpy",
      "predict",
      "strategies",
      "ws",
      "pandas"
    ],
    "line_additions": null,
    "line_deletions": null,
    "lines": 37,
    "lineno": 1,
    "cursorpos": 1,
    "is_write": true,
    "category": "coding",
    "created_at": "2025-04-09T19:06:23Z",
    "user_id": "1b7db2bc-8fbb-4a77-a51f-ea1943e20993",
    "user_agent_id": "a3a6b697-8da5-48cf-8984-cc441c410071",
    "machine_name_id": "8e4f98f0-d325-4088-af2f-e0ee5b89dfda"
  },
  {
    "id": "3ede8494-f32b-4f46-8de8-ef95efbd427a",
    "entity": "/Users/nikolaiborbe/Documents/Complexity/mimir/src/main.py",
    "type": "file",
    "time": 1744225513.663433,
    "project": "mimir",
    "project_root_count": 6,
    "branch": "main",
    "language": "Python",
    "dependencies": [
      "numpy",
      "time",
      "predict",
      "strategies",
      "ws",
      "pandas"
    ],
    "line_additions": null,
    "line_deletions": null,
    "lines": 38,
    "lineno": 2,
    "cursorpos": 13,
    "is_write": true,
    "category": "coding",
    "created_at": "2025-04-09T19:06:23Z",
    "user_id": "1b7db2bc-8fbb-4a77-a51f-ea1943e20993",
    "user_agent_id": "a3a6b697-8da5-48cf-8984-cc441c410071",
    "machine_name_id": "8e4f98f0-d325-4088-af2f-e0ee5b89dfda"
  },
  {
    "id": "b3ab9b2f-8ae9-4a20-8221-bbb00deaa802",
    "entity": "/Users/nikolaiborbe/Documents/Complexity/mimir/src/main.py",
    "type": "file",
    "time": 1744225515.193029,
    "project": "mimir",
    "project_root_count": 6,
    "branch": "main",
    "language": "Python",
    "dependencies": [
      "numpy",
      "time",
      "predict",
      "strategies",
      "ws",
      "pandas"
    ],
    "line_additions": null,
    "line_deletions": null,
    "lines": 38,
    "lineno": 2,
    "cursorpos": 1,
    "is_write": true,
    "category": "coding",
    "created_at": "2025-04-09T19:06:23Z",
    "user_id": "1b7db2bc-8fbb-4a77-a51f-ea1943e20993",
    "user_agent_id": "a3a6b697-8da5-48cf-8984-cc441c410071",
    "machine_name_id": "8e4f98f0-d325-4088-af2f-e0ee5b89dfda"
  },
  {
    "id": "2b3ca99f-8e24-4152-8ed9-29fdbf2264e4",
    "entity": "/Users/nikolaiborbe/Documents/Complexity/mimir/src/main.py",
    "type": "file",
    "time": 1744225520.837166,
    "project": "mimir",
    "project_root_count": 6,
    "branch": "main",
    "language": "Python",
    "dependencies": [
      "numpy",
      "time",
      "predict",
      "strategies",
      "ws",
      "pandas"
    ],
    "line_additions": null,
    "line_deletions": null,
    "lines": 39,
    "lineno": 29,
    "cursorpos": 28,
    "is_write": true,
    "category": "coding",
    "created_at": "2025-04-09T19:06:23Z",
    "user_id": "1b7db2bc-8fbb-4a77-a51f-ea1943e20993",
    "user_agent_id": "a3a6b697-8da5-48cf-8984-cc441c410071",
    "machine_name_id": "8e4f98f0-d325-4088-af2f-e0ee5b89dfda"
  },
  {
    "id": "47e8144c-041b-4b12-8c02-18a5684f43ef",
    "entity": "/Users/nikolaiborbe/Documents/Complexity/mimir/src/main.py",
    "type": "file",
    "time": 1744225582.14446,
    "project": "mimir",
    "project_root_count": 6,
    "branch": "main",
    "language": "Python",
    "dependencies": [
      "numpy",
      "predict",
      "time",
      "strategies",
      "ws",
      "pandas"
    ],
    "line_additions": null,
    "line_deletions": null,
    "lines": 37,
    "lineno": 21,
    "cursorpos": 13,
    "is_write": true,
    "category": "coding",
    "created_at": "2025-04-09T19:06:22Z",
    "user_id": "1b7db2bc-8fbb-4a77-a51f-ea1943e20993",
    "user_agent_id": "a3a6b697-8da5-48cf-8984-cc441c410071",
    "machine_name_id": "8e4f98f0-d325-4088-af2f-e0ee5b89dfda"
  }
]