[
  {
    "id": "df3d9a13-34d2-4ece-bcd6-83987d3035c2",
    "entity": "C:/Users/nikol/MAIN/programmering/Propulse/engine-software-2025-v0/build/Debug/engine-software-2025-v0.map",
    "type": "file",
    "time": 1740829542.7214,
    "project": "engine-software-2025-v0",
    "project_root_count": 7,
    "branch": "main",
    "language": null,
    "dependencies": [],
    "line_additions": null,
    "line_deletions": null,
    "lines": 105633,
    "lineno": 1,
    "cursorpos": 1,
    "is_write": false,
    "category": "coding",
    "created_at": "2025-03-01T11:48:28Z",
    "user_id": "1b7db2bc-8fbb-4a77-a51f-ea1943e20993",
    "user_agent_id": "1a713c80-b717-4cad-991b-f998d0743ba7",
    "machine_name_id": "187acaf3-e3c6-4b6d-ab77-4d9cd4a079e2"
  },
  {
    "id": "c5e6ac37-b5e0-414d-a71c-c37abad299a4",
    "entity": "C:/Users/nikol/MAIN/programmering/Propulse/engine-software-2025-v0/Core/Src/app_threadx.c",
    "type": "file",
    "time": 1740829543.201345,
    "project": "engine-software-2025-v0",
    "project_root_count": 7,
    "branch": "main",
    "language": "C",
    "dependencies": [
      "stdint",
      "reset",
      "threadpool",
      "autovent",
      "pressure",
      "app_threadx",
      "fsm",
      "status",
      "ereg",
      "encoder",
      "can-data",
      "cliudp",
      "thermo"
    ],
    "line_additions": null,
    "line_deletions": null,
    "lines": 188,
    "lineno": 89,
    "cursorpos": 117,
    "is_write": false,
    "category": "coding",
    "created_at": "2025-03-01T11:48:28Z",
    "user_id": "1b7db2bc-8fbb-4a77-a51f-ea1943e20993",
    "user_agent_id": "1a713c80-b717-4cad-991b-f998d0743ba7",
    "machine_name_id": "187acaf3-e3c6-4b6d-ab77-4d9cd4a079e2"
  },
  {
    "id": "387d7507-0fbf-41fb-91dc-2a9ebe16a43d",
    "entity": "C:/Users/nikol/MAIN/programmering/Propulse/engine-software-2025-v0/build/Debug/engine-software-2025-v0.map",
    "type": "file",
    "time": 1740829599.697761,
    "project": "engine-software-2025-v0",
    "project_root_count": 7,
    "branch": "main",
    "language": null,
    "dependencies": [],
    "line_additions": null,
    "line_deletions": null,
    "lines": 105633,
    "lineno": 1,
    "cursorpos": 1,
    "is_write": false,
    "category": "coding",
    "created_at": "2025-03-01T11:48:28Z",
    "user_id": "1b7db2bc-8fbb-4a77-a51f-ea1943e20993",
    "user_agent_id": "1a713c80-b717-4cad-991b-f998d0743ba7",
    "machine_name_id": "187acaf3-e3c6-4b6d-ab77-4d9cd4a079e2"
  },
  {
    "id": "603ac62f-10c7-40a1-85a5-42a702d122df",
    "entity": "C:/Users/nikol/MAIN/programmering/Propulse/engine-software-2025-v0/Core/Src/app_threadx.c",
    "type": "file",
    "time": 1740829600.661161,
    "project": "engine-software-2025-v0",
    "project_root_count": 7,
    "branch": "main",
    "language": "C",
    "dependencies": [
      "stdint",
      "reset",
      "threadpool",
      "autovent",
      "pressure",
      "app_threadx",
      "fsm",
      "status",
      "ereg",
      "encoder",
      "can-data",
      "cliudp",
      "thermo"
    ],
    "line_additions": null,
    "line_deletions": null,
    "lines": 188,
    "lineno": 90,
    "cursorpos": 43,
    "is_write": false,
    "category": "coding",
    "created_at": "2025-03-01T11:48:28Z",
    "user_id": "1b7db2bc-8fbb-4a77-a51f-ea1943e20993",
    "user_agent_id": "1a713c80-b717-4cad-991b-f998d0743ba7",
    "machine_name_id": "187acaf3-e3c6-4b6d-ab77-4d9cd4a079e2"
  },
  {
    "id": "82e11367-f900-4834-a010-c41f5eea6e37",
    "entity": "C:/Users/nikol/MAIN/programmering/Propulse/engine-software-2025-v0/Core/Src/app_threadx.c",
    "type": "file",
    "time": 1740829710.029422,
    "project": "engine-software-2025-v0",
    "project_root_count": 7,
    "branch": "main",
    "language": "C",
    "dependencies": [
      "stdint",
      "reset",
      "threadpool",
      "autovent",
      "pressure",
      "app_threadx",
      "fsm",
      "status",
      "ereg",
      "encoder",
      "can-data",
      "cliudp",
      "thermo"
    ],
    "line_additions": null,
    "line_deletions": null,
    "lines": 188,
    "lineno": 91,
    "cursorpos": 4,
    "is_write": false,
    "category": "coding",
    "created_at": "2025-03-01T11:48:27Z",
    "user_id": "1b7db2bc-8fbb-4a77-a51f-ea1943e20993",
    "user_agent_id": "1a713c80-b717-4cad-991b-f998d0743ba7",
    "machine_name_id": "187acaf3-e3c6-4b6d-ab77-4d9cd4a079e2"
  }
]